GoYuyanRumenjiaochengCYuyanZhongwenwang/README.md
GoYuyanRumenjiaochengCYuyanZhongwenwang/__init__.py
GoYuyanRumenjiaochengCYuyanZhongwenwang/__main__.py
GoYuyanRumenjiaochengCYuyanZhongwenwang/file.epub
GoYuyanRumenjiaochengCYuyanZhongwenwang/index.html
GoYuyanRumenjiaochengCYuyanZhongwenwang/css/__init__.py
GoYuyanRumenjiaochengCYuyanZhongwenwang/css/annotations.css
GoYuyanRumenjiaochengCYuyanZhongwenwang/css/main.css
GoYuyanRumenjiaochengCYuyanZhongwenwang/css/normalize.css
GoYuyanRumenjiaochengCYuyanZhongwenwang/css/popup.css
GoYuyanRumenjiaochengCYuyanZhongwenwang/font/__init__.py
GoYuyanRumenjiaochengCYuyanZhongwenwang/font/fontello.eot
GoYuyanRumenjiaochengCYuyanZhongwenwang/font/fontello.svg
GoYuyanRumenjiaochengCYuyanZhongwenwang/font/fontello.ttf
GoYuyanRumenjiaochengCYuyanZhongwenwang/font/fontello.woff
GoYuyanRumenjiaochengCYuyanZhongwenwang/img/__init__.py
GoYuyanRumenjiaochengCYuyanZhongwenwang/img/annotator-glyph-sprite.png
GoYuyanRumenjiaochengCYuyanZhongwenwang/img/annotator-icon-sprite.png
GoYuyanRumenjiaochengCYuyanZhongwenwang/img/apple-touch-icon.png
GoYuyanRumenjiaochengCYuyanZhongwenwang/img/cancelfullscreen.png
GoYuyanRumenjiaochengCYuyanZhongwenwang/img/close.png
GoYuyanRumenjiaochengCYuyanZhongwenwang/img/fullscreen.png
GoYuyanRumenjiaochengCYuyanZhongwenwang/img/loader.gif
GoYuyanRumenjiaochengCYuyanZhongwenwang/img/menu-icon.png
GoYuyanRumenjiaochengCYuyanZhongwenwang/img/save.png
GoYuyanRumenjiaochengCYuyanZhongwenwang/img/saved.png
GoYuyanRumenjiaochengCYuyanZhongwenwang/img/settings-s.png
GoYuyanRumenjiaochengCYuyanZhongwenwang/img/settings.png
GoYuyanRumenjiaochengCYuyanZhongwenwang/img/star.png
GoYuyanRumenjiaochengCYuyanZhongwenwang/js/__init__.py
GoYuyanRumenjiaochengCYuyanZhongwenwang/js/epub.js
GoYuyanRumenjiaochengCYuyanZhongwenwang/js/epub.min.js
GoYuyanRumenjiaochengCYuyanZhongwenwang/js/epub.min.map
GoYuyanRumenjiaochengCYuyanZhongwenwang/js/hooks.min.js
GoYuyanRumenjiaochengCYuyanZhongwenwang/js/hooks.min.map
go_yuyan_rumenjiaocheng_c_yuyan_zhongwenwang-2024.3.5.0.dist-info/METADATA
go_yuyan_rumenjiaocheng_c_yuyan_zhongwenwang-2024.3.5.0.dist-info/WHEEL
go_yuyan_rumenjiaocheng_c_yuyan_zhongwenwang-2024.3.5.0.dist-info/entry_points.txt
go_yuyan_rumenjiaocheng_c_yuyan_zhongwenwang-2024.3.5.0.dist-info/top_level.txt
go_yuyan_rumenjiaocheng_c_yuyan_zhongwenwang-2024.3.5.0.dist-info/RECORD
